crisp_status_reporter/__init__.py
crisp_status_reporter-1.1.1.dist-info/AUTHORS
crisp_status_reporter-1.1.1.dist-info/LICENSE
crisp_status_reporter-1.1.1.dist-info/METADATA
crisp_status_reporter-1.1.1.dist-info/WHEEL
crisp_status_reporter-1.1.1.dist-info/top_level.txt
crisp_status_reporter-1.1.1.dist-info/RECORD
